jpyreport/__init__.py
jpyreport/junit_parser.py
jpyreport/report.js
jpyreport/report_items.py
jpyreport/runner.py
jpyreport/style.css
jpyreport-1.0.0.post1.dist-info/DESCRIPTION.rst
jpyreport-1.0.0.post1.dist-info/METADATA
jpyreport-1.0.0.post1.dist-info/RECORD
jpyreport-1.0.0.post1.dist-info/WHEEL
jpyreport-1.0.0.post1.dist-info/entry_points.txt
jpyreport-1.0.0.post1.dist-info/metadata.json
jpyreport-1.0.0.post1.dist-info/pbr.json
jpyreport-1.0.0.post1.dist-info/top_level.txt
